subpair/__init__.py
subpair/__main__.py
subpair/cosine.py
subpair/minimize.py
subpair-0.1.1.dist-info/LICENSE
subpair-0.1.1.dist-info/METADATA
subpair-0.1.1.dist-info/WHEEL
subpair-0.1.1.dist-info/top_level.txt
subpair-0.1.1.dist-info/RECORD
