Metadata-Version: 2.1
Name: subpair
Version: 0.1.1
Summary: Fast pairwise cosine distance calculation and numba accelerated evolutionary matrix subset extraction 
Author-email: lfrati <lfrati.github@gmail.com>
License: MIT
Project-URL: Homepage, https://github.com/lfrati/subpair
Keywords: numpy,numba,evolution,pairwise-cosine
Classifier: License :: OSI Approved :: MIT License
Classifier: Programming Language :: Python :: 3
Requires-Python: >=3.9
License-File: LICENSE
Requires-Dist: numpy
Requires-Dist: numba
Requires-Dist: tqdm
Provides-Extra: dev
Requires-Dist: bumpver ; extra == 'dev'
Requires-Dist: pip-tools ; extra == 'dev'
Requires-Dist: build ; extra == 'dev'
Requires-Dist: twine ; extra == 'dev'
Requires-Dist: matplotlib ; extra == 'dev'
Requires-Dist: ipython ; extra == 'dev'
Provides-Extra: testing
Requires-Dist: pytest ; extra == 'testing'
Requires-Dist: scipy ; extra == 'testing'
Requires-Dist: scikit-learn ; extra == 'testing'
